README.md
setup.py
oneroster_client/__init__.py
oneroster_client/api_client.py
oneroster_client/configuration.py
oneroster_client/rest.py
oneroster_client/api/__init__.py
oneroster_client/api/academic_sessions_management_api.py
oneroster_client/api/categories_management_api.py
oneroster_client/api/classes_management_api.py
oneroster_client/api/courses_management_api.py
oneroster_client/api/demographics_management_api.py
oneroster_client/api/enrollments_management_api.py
oneroster_client/api/grading_periods_management_api.py
oneroster_client/api/line_items_management_api.py
oneroster_client/api/orgs_management_api.py
oneroster_client/api/resources_management_api.py
oneroster_client/api/results_management_api.py
oneroster_client/api/schools_management_api.py
oneroster_client/api/students_management_api.py
oneroster_client/api/teachers_management_api.py
oneroster_client/api/terms_management_api.py
oneroster_client/api/users_management_api.py
oneroster_client/models/__init__.py
oneroster_client/models/academic_session_type.py
oneroster_client/models/academic_session_type_all_of.py
oneroster_client/models/base_type.py
oneroster_client/models/categories_type.py
oneroster_client/models/category_type.py
oneroster_client/models/category_type_all_of.py
oneroster_client/models/class_type.py
oneroster_client/models/class_type_all_of.py
oneroster_client/models/classes_type.py
oneroster_client/models/course_type.py
oneroster_client/models/course_type_all_of.py
oneroster_client/models/courses_type.py
oneroster_client/models/demographic_type.py
oneroster_client/models/demographic_type_all_of.py
oneroster_client/models/demographics_type.py
oneroster_client/models/enrollment_type.py
oneroster_client/models/enrollment_type_all_of.py
oneroster_client/models/enrollments_type.py
oneroster_client/models/guid_ref_type.py
oneroster_client/models/guid_type.py
oneroster_client/models/identifier_type.py
oneroster_client/models/imsx_code_minor_field_type.py
strongmind_oneroster_client.egg-info/PKG-INFO
strongmind_oneroster_client.egg-info/SOURCES.txt
strongmind_oneroster_client.egg-info/dependency_links.txt
strongmind_oneroster_client.egg-info/requires.txt
strongmind_oneroster_client.egg-info/top_level.txt
